LICENSE
MANIFEST.in
README.rst
setup.py
cmsplugin_contact/__init__.py
cmsplugin_contact/admin.py
cmsplugin_contact/cms_plugins.py
cmsplugin_contact/forms.py
cmsplugin_contact/middleware.py
cmsplugin_contact/models.py
cmsplugin_contact/settings.py
cmsplugin_contact/utils.py
cmsplugin_contact.egg-info/PKG-INFO
cmsplugin_contact.egg-info/SOURCES.txt
cmsplugin_contact.egg-info/dependency_links.txt
cmsplugin_contact.egg-info/not-zip-safe
cmsplugin_contact.egg-info/pbr.json
cmsplugin_contact.egg-info/top_level.txt
cmsplugin_contact/locale/de/LC_MESSAGES/django.mo
cmsplugin_contact/locale/es/LC_MESSAGES/django.mo
cmsplugin_contact/locale/fr/LC_MESSAGES/django.mo
cmsplugin_contact/locale/it/LC_MESSAGES/django.mo
cmsplugin_contact/locale/no/LC_MESSAGES/django.mo
cmsplugin_contact/locale/pl/LC_MESSAGES/django.mo
cmsplugin_contact/locale/pt/LC_MESSAGES/django.mo
cmsplugin_contact/locale/pt_BR/LC_MESSAGES/django.mo
cmsplugin_contact/locale/ru/LC_MESSAGES/django.mo
cmsplugin_contact/locale/sl/LC_MESSAGES/django.mo
cmsplugin_contact/migrations/0001_initial.py
cmsplugin_contact/migrations/0002_auto__chg_field_contact_thanks.py
cmsplugin_contact/migrations/0003_auto__add_field_contact_form_name.py
cmsplugin_contact/migrations/0004_add_field_Contact_form_layout.py
cmsplugin_contact/migrations/0005_auto__del_field_contact_content_label__del_field_contact_subject_label.py
cmsplugin_contact/migrations/0006_fix_table_names.py
cmsplugin_contact/migrations/0007_add_url_field.py
cmsplugin_contact/migrations/__init__.py
cmsplugin_contact/migrations_django/0001_initial.py
cmsplugin_contact/migrations_django/0002_auto_20160810_1130.py
cmsplugin_contact/migrations_django/0003_auto_20161107_1614.py
cmsplugin_contact/migrations_django/__init__.py
cmsplugin_contact/nospam/__init__.py
cmsplugin_contact/nospam/fields.py
cmsplugin_contact/nospam/forms.py
cmsplugin_contact/nospam/utils.py
cmsplugin_contact/nospam/widgets.py
cmsplugin_contact/templates/cmsplugin_contact/contact.html
cmsplugin_contact/templates/cmsplugin_contact/email.txt
cmsplugin_contact/templates/cmsplugin_contact/subject.txt
cmsplugin_contact/templates/cmsplugin_contact/admin/plugin_change_form.html