Metadata-Version: 1.1
Name: cmsplugin-contact
Version: 1.1.3
Summary: Extendable contact form plugin for Django CMS with spam protection and i18n
Home-page: http://github.com/maccesch/cmsplugin-contact
Author: Maccesch
Author-email: maccesch@gmail.com
License: UNKNOWN
Keywords: contact form django cms django-cms spam protection email
Platform: UNKNOWN
Classifier: Development Status :: 5 - Production/Stable
Classifier: Environment :: Web Environment
Classifier: Intended Audience :: Developers
Classifier: License :: OSI Approved :: BSD License
Classifier: Operating System :: OS Independent
Classifier: Programming Language :: Python
Classifier: Framework :: Django
